LICENSE.md
README.md
setup.py
pyialarmxr/__init__.py
pyialarmxr/pyialarmxr.py
pyialarmxr_homeassistant.egg-info/PKG-INFO
pyialarmxr_homeassistant.egg-info/SOURCES.txt
pyialarmxr_homeassistant.egg-info/dependency_links.txt
pyialarmxr_homeassistant.egg-info/requires.txt
pyialarmxr_homeassistant.egg-info/top_level.txt
pyialarmxr_homeassistant.egg-info/zip-safe