Metadata-Version: 2.1
Name: pyialarmxr-homeassistant
Version: 1.0.18
Summary: A simple library to interface with iAlarmXR systems, built for use with Home Assistant
Home-page: https://github.com/bigmoby/pyialarmxr
Author: Fabio Mauro, Ludovico de Nittis
Author-email: bigmoby.pyialarmxr@gmail.com
License: MIT License
Platform: any
Classifier: Development Status :: 4 - Beta
Classifier: Intended Audience :: Developers
Classifier: Programming Language :: Python :: 3
Requires-Python: >=3.8
License-File: LICENSE.md
